Workbook

Sheet Resumen Ejecutivo
A1: SIGAB — Resumen Ejecutivo Financiero
A3: Proyecto | B3: SIGAB — Sistema Integral de Gestión de Activos Biomédicos V2.0
A4: Sector | B4: HealthTech B2G — Gestión hospitalaria de equipo biomédico
A5: Horizonte | B5: 5 años (2026-2030)
A6: Modelo de negocio | B6: Asset-Light: despliegue único + licencia anual on-premise
A8: INDICADORES FINANCIEROS CLAVE
A9: KPI | B9: Valor | C9: Unidad | D9: Interpretación
A10: Inversión inicial total | B10: ='Inversión Inicial'!B8 -> 850000 | C10: MXN | D10: Capital requerido para iniciar
A11: Ingresos año 5 | B11: =Ingresos!F10 -> 5130999.6 | C11: MXN | D11: Ventas al final del horizonte
A12: Utilidad neta año 5 | B12: ='Pro-Forma'!F12 -> 1191819.9 | C12: MXN | D12: Resultado después de ISR
A13: Flujo de caja año 5 | B13: ='Pro-Forma'!F15 -> 1267819.9 | C13: MXN | D13: Efectivo operativo al año 5
A14: Hospitales clientes año 5 | B14: =Ingresos!F6 -> 33.8 | C14: hosp | D14: Base de clientes acumulada
A15: Punto de equilibrio año 1 | B15: ='Punto de Equilibrio'!B9 -> 3.5111111 | C15: hospitales | D15: Mínimo para cubrir costos fijos
A16: TMAR | B16: ='VPN TMAR TIR'!B7 -> 0.18 | C16: % | D16: Rendimiento mínimo exigido
A17: VPN @ TMAR | B17: ='VPN TMAR TIR'!B19 -> 493187.06 | C17: MXN | D17: Valor generado hoy
A18: TIR | B18: ='VPN TMAR TIR'!B20 -> 0.32580209 | C18: % | D18: Rentabilidad intrínseca
A19: Decisión | B19: =IF(AND('VPN TMAR TIR'!B19>0,'VPN TMAR TIR'!B20>'VPN TMAR TIR'!B7),"INVERTIR OK","REVISAR") -> INVERTIR OK | D19: Regla de oro: VPN>0 y TIR>TMAR

Sheet Supuestos
A1: SIGAB — Supuestos del Modelo Financiero (5 años)
A2: Proyecto: Sistema Integral de Gestión de Activos Biomédicos
A3: Cliente objetivo: IMSS (HGR No.1 Tijuana como piloto) + hospitales públicos y privados
A4: Modelo: Asset-Light (Estrategia 2) — Hospital compra hardware; SIGAB cobra despliegue + licencia
A5: Horizonte: 5 años | Moneda: MXN | Tasa ISR: 30%
A7: INGRESOS — parámetros
A8: Cuota única de despliegue por hospital (MXN) | B8: 30000 | G8: Instalación, configuración, capacitación inicial
A9: Licencia anual por hospital — año 1 (MXN) | B9: 120000 | G9: Incluye soporte L2, actualizaciones, IA Copilot
A10: Licencia anual renovación años 2-5 (MXN) | B10: 120000 | G10: Renovación con precio estable
A11: Crecimiento anual de tarifas (inflación) | B11: 0.04 | G11: IPC promedio México últimos 5 años
A12: Churn anual (% hospitales que no renuevan) | B12: 0.05 | G12: Bajo por lock-in normativo NOM-016
A14: HOSPITALES ACUMULADOS POR AÑO
A15: Métrica | B15: Año 1 | C15: Año 2 | D15: Año 3 | E15: Año 4 | F15: Año 5 | G15: Notas
A16: Hospitales NUEVOS / año | B16: 3 | C16: 5 | D16: 7 | E16: 9 | F16: 11 | G16: Crecimiento conservador post-piloto IMSS
A17: Hospitales ACUMULADOS (total) | B17: =B16 -> 3 | C17: =B17+C16 -> 8 | D17: =C17+D16 -> 15 | E17: =D17+E16 -> 24 | F17: =E17+F16 -> 35
A19: ESTRUCTURA DE COSTOS
A20: Costo variable (% de ingresos) — soporte, hosting local, mantenimiento | B20: 0.4 | G20: Soporte L1, visitas técnicas, gastos despliegue
A21: Costos fijos año 1 — equipo fundador + freelancer | B21: 240000 | G21: 2 fundadores @ $100k + $40k gastos
A22: Costos fijos año 2 | B22: 480000 | G22: Fundadores completo + 1 KAM + mkt
A23: Costos fijos año 3 | B23: 720000 | G23: Equipo de 4 (2 devs + 1 KAM + 1 admin)
A24: Costos fijos año 4 | B24: 1000000 | G24: Equipo de 5-6 (+1 dev, mkt ampliado)
A25: Costos fijos año 5 | B25: 1300000 | G25: Equipo consolidado 7-8 personas
A27: INVERSIÓN, DEPRECIACIÓN E IMPUESTOS
A28: Activo fijo tangible (equipo cómputo + oficina) | B28: 80000 | G28: ThinkCentre + monitores + mobiliario
A29: Activo intangible (desarrollo software capitalizado) | B29: 300000 | G29: 8 meses dev @ valor de mercado
A30: Capital de trabajo inicial | B30: 350000 | G30: 12 meses OpEx bajo escenario mínimo
A31: Gastos preoperativos (legal, permisos, marca) | B31: 120000 | G31: SAT, IMPI, constitución SA de CV
A32: Vida útil activo fijo (años) | B32: 5 | G32: Línea recta fiscal
A33: Tasa ISR | B33: 0.3 | G33: LISR México
A34: Tasa libre de riesgo (CETES 28d) | B34: 0.0925 | G34: CETES Mar-2026 (Banxico)
A35: Prima de riesgo (nuevo mercado HealthTech B2G) | B35: 0.0875 | G35: Rango 8-15% por nuevo mercado (PDF Prof. Piña)

Sheet Inversión Inicial
A1: SIGAB — Inversión Inicial en Activo Fijo y Preoperativos
A3: Concepto | B3: Monto (MXN) | C3: % del total | D3: Descripción
A4: Activo fijo tangible (ThinkCentre + monitor + teclado + mobiliario) | B4: =Supuestos!B28 -> 80000 | C4: =B4/$B$8 -> 0.094117647 | D4: Equipo de cómputo, periféricos, escritorio
A5: Activo intangible (desarrollo de software) | B5: =Supuestos!B29 -> 300000 | C5: =B5/$B$8 -> 0.35294118 | D5: Capitalización de 8 meses de desarrollo
A6: Capital de trabajo | B6: =Supuestos!B30 -> 350000 | C6: =B6/$B$8 -> 0.41176471 | D6: 12 meses de OpEx mínimo
A7: Gastos preoperativos (legal, permisos, marca, pagos iniciales) | B7: =Supuestos!B31 -> 120000 | C7: =B7/$B$8 -> 0.14117647 | D7: SAT, IMPI, notario, constitución
A8: TOTAL INVERSIÓN INICIAL | B8: =SUM(B4:B7) -> 850000 | C8: =SUM(C4:C7) -> 1
A11: DEPRECIACIÓN Y AMORTIZACIÓN ANUAL
A12: Concepto | B12: Monto anual | C12: Método | D12: Notas
A13: Depreciación activo fijo tangible | B13: =Supuestos!B28/Supuestos!B32 -> 16000 | C13: Línea recta 5 años | D13: ISR: 10-25% según activo; usamos 20%
A14: Amortización activo intangible | B14: =Supuestos!B29/Supuestos!B32 -> 60000 | C14: Línea recta 5 años | D14: Software desarrollado internamente
A15: TOTAL DEP + AMORT (anual) | B15: =B13+B14 -> 76000

Sheet Ingresos
A1: SIGAB — Proyección de Ingresos 5 años (Modelo Asset-Light)
A3: Concepto | B3: Año 1 | C3: Año 2 | D3: Año 3 | E3: Año 4 | F3: Año 5 | G3: Fórmula
A4: Hospitales NUEVOS del año | B4: =Supuestos!B16 -> 3 | C4: =Supuestos!C16 -> 5 | D4: =Supuestos!D16 -> 7 | E4: =Supuestos!E16 -> 9 | F4: =Supuestos!F16 -> 11 | G4: Link a Supuestos
A5: Hospitales RENOVANDO | B5: 0 | C5: =Supuestos!B17*(1-Supuestos!$B$12) -> 2.85 | D5: =Supuestos!C17*(1-Supuestos!$B$12) -> 7.6 | E5: =Supuestos!D17*(1-Supuestos!$B$12) -> 14.25 | F5: =Supuestos!E17*(1-Supuestos!$B$12) -> 22.8 | G5: Acumulados previos × (1-churn)
A6: Hospitales ACTIVOS (total) | B6: =B4+B5 -> 3 | C6: =C4+C5 -> 7.85 | D6: =D4+D5 -> 14.6 | E6: =E4+E5 -> 23.25 | F6: =F4+F5 -> 33.8
A8: Ingresos por DESPLIEGUE (nuevos × cuota) | B8: =B4*Supuestos!$B$8*(1+Supuestos!$B$11)^0 -> 90000 | C8: =C4*Supuestos!$B$8*(1+Supuestos!$B$11)^1 -> 156000 | D8: =D4*Supuestos!$B$8*(1+Supuestos!$B$11)^2 -> 227136 | E8: =E4*Supuestos!$B$8*(1+Supuestos!$B$11)^3 -> 303713.28 | F8: =F4*Supuestos!$B$8*(1+Supuestos!$B$11)^4 -> 386053.32
A9: Ingresos por LICENCIAS (activos × tarifa) | B9: =B6*Supuestos!$B$9*(1+Supuestos!$B$11)^0 -> 360000 | C9: =C6*Supuestos!$B$9*(1+Supuestos!$B$11)^1 -> 979680 | D9: =D6*Supuestos!$B$9*(1+Supuestos!$B$11)^2 -> 1894963.2 | E9: =E6*Supuestos!$B$9*(1+Supuestos!$B$11)^3 -> 3138370.6 | F9: =F6*Supuestos!$B$9*(1+Supuestos!$B$11)^4 -> 4744946.3
A10: INGRESOS TOTALES | B10: =B8+B9 -> 450000 | C10: =C8+C9 -> 1135680 | D10: =D8+D9 -> 2122099.2 | E10: =E8+E9 -> 3442083.8 | F10: =F8+F9 -> 5130999.6
A12: Crecimiento anual (%) | C12: =(C10-B10)/B10 -> 1.5237333 | D12: =(D10-C10)/C10 -> 0.86857143 | E12: =(E10-D10)/D10 -> 0.62201835 | F12: =(F10-E10)/E10 -> 0.49066667

Sheet Costos de Producción
A1: SIGAB — Estructura de Costos de Producción 5 años
A3: Concepto | B3: Año 1 | C3: Año 2 | D3: Año 3 | E3: Año 4 | F3: Año 5 | G3: Base
A4: Costo variable (soporte, hosting, visitas técnicas) | B4: =Ingresos!B10*Supuestos!$B$20 -> 180000 | C4: =Ingresos!C10*Supuestos!$B$20 -> 454272 | D4: =Ingresos!D10*Supuestos!$B$20 -> 848839.68 | E4: =Ingresos!E10*Supuestos!$B$20 -> 1376833.5 | F4: =Ingresos!F10*Supuestos!$B$20 -> 2052399.9 | G4: 40% de ingresos
A5: Costos fijos (salarios + administración + marketing) | B5: =Supuestos!B21 -> 240000 | C5: =Supuestos!B22 -> 480000 | D5: =Supuestos!B23 -> 720000 | E5: =Supuestos!B24 -> 1000000 | F5: =Supuestos!B25 -> 1300000 | G5: Link Supuestos
A6: COSTO TOTAL DE PRODUCCIÓN | B6: =B4+B5 -> 420000 | C6: =C4+C5 -> 934272 | D6: =D4+D5 -> 1568839.7 | E6: =E4+E5 -> 2376833.5 | F6: =F4+F5 -> 3352399.9
A9: DESGLOSE DE COSTOS FIJOS (ilustrativo año 3)
A10: Concepto | B10: Monto anual | C10: % del fijo | D10: Notas
A11: Salarios desarrolladores (2 personas) | B11: 480000 | C11: =B11/$B$15 -> 0.66666667 | D11: Full-stack senior + junior
A12: Salario comercial / KAM | B12: 180000 | C12: =B12/$B$15 -> 0.25 | D12: Gestión IMSS y clientes privados
A13: Marketing digital + asistencia a ferias | B13: 40000 | C13: =B13/$B$15 -> 0.055555556 | D13: Google Ads + HIMSS
A14: Servicios: oficina, luz, internet, software | B14: 20000 | C14: =B14/$B$15 -> 0.027777778 | D14: Coworking Tijuana
A15: Total fijo año 3 (cuadre) | B15: =SUM(B11:B14) -> 720000

Sheet Pro-Forma
A1: SIGAB — Estado de Resultados Pro-Forma (5 años)
A3: Concepto | B3: Año 1 | C3: Año 2 | D3: Año 3 | E3: Año 4 | F3: Año 5
A4: (+) Ingresos | B4: =Ingresos!B10 -> 450000 | C4: =Ingresos!C10 -> 1135680 | D4: =Ingresos!D10 -> 2122099.2 | E4: =Ingresos!E10 -> 3442083.8 | F4: =Ingresos!F10 -> 5130999.6
A5: (−) Costo de ventas (variable) | B5: ='Costos de Producción'!B4 -> 180000 | C5: ='Costos de Producción'!C4 -> 454272 | D5: ='Costos de Producción'!D4 -> 848839.68 | E5: ='Costos de Producción'!E4 -> 1376833.5 | F5: ='Costos de Producción'!F4 -> 2052399.9
A6: (=) Utilidad bruta | B6: =B4-B5 -> 270000 | C6: =C4-C5 -> 681408 | D6: =D4-D5 -> 1273259.5 | E6: =E4-E5 -> 2065250.3 | F6: =F4-F5 -> 3078599.8
A7: Margen bruto (%) | B7: =B6/B4 -> 0.6 | C7: =C6/C4 -> 0.6 | D7: =D6/D4 -> 0.6 | E7: =E6/E4 -> 0.6 | F7: =F6/F4 -> 0.6
A8: (−) Gastos operativos fijos | B8: ='Costos de Producción'!B5 -> 240000 | C8: ='Costos de Producción'!C5 -> 480000 | D8: ='Costos de Producción'!D5 -> 720000 | E8: ='Costos de Producción'!E5 -> 1000000 | F8: ='Costos de Producción'!F5 -> 1300000
A9: (−) Depreciación + Amortización | B9: ='Inversión Inicial'!B15 -> 76000 | C9: ='Inversión Inicial'!B15 -> 76000 | D9: ='Inversión Inicial'!B15 -> 76000 | E9: ='Inversión Inicial'!B15 -> 76000 | F9: ='Inversión Inicial'!B15 -> 76000
A10: (=) EBIT (Utilidad operativa) | B10: =B6-B8-B9 -> -46000 | C10: =C6-C8-C9 -> 125408 | D10: =D6-D8-D9 -> 477259.52 | E10: =E6-E8-E9 -> 989250.3 | F10: =F6-F8-F9 -> 1702599.8
A11: (−) ISR 30% (solo si EBIT > 0) | B11: =MAX(0,B10)*Supuestos!$B$33 -> 0 | C11: =MAX(0,C10)*Supuestos!$B$33 -> 37622.4 | D11: =MAX(0,D10)*Supuestos!$B$33 -> 143177.86 | E11: =MAX(0,E10)*Supuestos!$B$33 -> 296775.09 | F11: =MAX(0,F10)*Supuestos!$B$33 -> 510779.94
A12: (=) Utilidad neta | B12: =B10-B11 -> -46000 | C12: =C10-C11 -> 87785.6 | D12: =D10-D11 -> 334081.66 | E12: =E10-E11 -> 692475.21 | F12: =F10-F11 -> 1191819.9
A13: Margen neto (%) | B13: =B12/B4 -> -0.10222222 | C13: =C12/C4 -> 0.07729783 | D13: =D12/D4 -> 0.15742981 | E13: =E12/E4 -> 0.20117907 | F13: =F12/F4 -> 0.2322783
A14: (+) Depreciación (no-cash) | B14: =B9 -> 76000 | C14: =C9 -> 76000 | D14: =D9 -> 76000 | E14: =E9 -> 76000 | F14: =F9 -> 76000
A15: (=) FLUJO DE CAJA OPERATIVO | B15: =B12+B14 -> 30000 | C15: =C12+C14 -> 163785.6 | D15: =D12+D14 -> 410081.66 | E15: =E12+E14 -> 768475.21 | F15: =F12+F14 -> 1267819.9

Sheet Punto de Equilibrio
A1: SIGAB — Análisis de Punto de Equilibrio (Año 1)
A3: Concepto | B3: Valor | C3: Notas
A4: Ingreso promedio por hospital-año (año 1) | B4: =(Ingresos!B10)/Ingresos!B6 -> 150000 | C4: Ingresos totales año 1 / hospitales activos
A5: Costo variable por hospital-año | B5: =B4*Supuestos!B20 -> 60000 | C5: Precio × % variable
A6: Margen de contribución por hospital | B6: =B4-B5 -> 90000 | C6: Cuánto aporta cada hospital a cubrir fijos
A7: Margen de contribución (%) | B7: =B6/B4 -> 0.6
A8: Costos fijos totales año 1 (OpEx + Dep/Amort) | B8: =Supuestos!B21+'Inversión Inicial'!B15 -> 316000 | C8: Sueldos + admin + depreciación
A9: PUNTO DE EQUILIBRIO (hospitales) | B9: =B8/B6 -> 3.5111111 | C9: Hospitales necesarios para cubrir costos fijos
A10: PUNTO DE EQUILIBRIO (ingresos MXN) | B10: =B8/B7 -> 526666.67 | C10: Ventas mínimas para cubrir costos fijos
A11: Hospitales reales año 1 | B11: =Ingresos!B6 -> 3 | C11: Si < punto de equilibrio, año 1 cierra con pérdida
A12: Margen de seguridad (%) | B12: =IF(B11>B9,(B11-B9)/B11,(B11-B9)/B9) -> -0.14556962
A15: PUNTO DE EQUILIBRIO POR AÑO (hospitales)
A16: Año | B16: Hospitales requeridos (BE) | C16: Hospitales reales
A17: Año 1 | B17: =(Supuestos!B21+'Inversión Inicial'!B15)/((Ingresos!B10/Ingresos!B6)*(1-Supuestos!$B$20)) -> 3.5111111 | C17: =Ingresos!B6 -> 3
A18: Año 2 | B18: =(Supuestos!B22+'Inversión Inicial'!B15)/((Ingresos!C10/Ingresos!C6)*(1-Supuestos!$B$20)) -> 6.4052667 | C18: =Ingresos!C6 -> 7.85
A19: Año 3 | B19: =(Supuestos!B23+'Inversión Inicial'!B15)/((Ingresos!D10/Ingresos!D6)*(1-Supuestos!$B$20)) -> 9.1274401 | C19: =Ingresos!D6 -> 14.6
A20: Año 4 | B20: =(Supuestos!B24+'Inversión Inicial'!B15)/((Ingresos!E10/Ingresos!E6)*(1-Supuestos!$B$20)) -> 12.113302 | C20: =Ingresos!E6 -> 23.25
A21: Año 5 | B21: =(Supuestos!B25+'Inversión Inicial'!B15)/((Ingresos!F10/Ingresos!F6)*(1-Supuestos!$B$20)) -> 15.107128 | C21: =Ingresos!F6 -> 33.8

Sheet VPN TMAR TIR
A1: SIGAB — VPN, TMAR y TIR
A3: CÁLCULO DE TMAR (Tasa Mínima Aceptable de Rendimiento)
A4: Componente | B4: Valor | E4: Fuente
A5: Tasa libre de riesgo (CETES 28d) | B5: =Supuestos!B34 -> 0.0925 | E5: Banxico — abril 2026
A6: Prima de riesgo | B6: =Supuestos!B35 -> 0.0875 | E6: Nuevo mercado HealthTech B2G (rango 8-15% PDF Prof. Piña)
A7: TMAR = Rf + Prima | B7: =B5+B6 -> 0.18 | E7: Piso mínimo de rentabilidad exigida
A10: FLUJOS DE CAJA DEL PROYECTO
A11: Año | B11: Flujo de caja | C11: Factor (1+TMAR)^n | D11: Valor Presente | E11: VP Acumulado
A12: Año 0 | B12: =-'Inversión Inicial'!B8 -> -850000 | C12: 1.0000 | D12: =B12 -> -850000 | E12: =D12 -> -850000
A13: Año 1 | B13: ='Pro-Forma'!B15 -> 30000 | C13: =(1+$B$7)^1 -> 1.18 | D13: =B13/C13 -> 25423.729 | E13: =E12+D13 -> -824576.27
A14: Año 2 | B14: ='Pro-Forma'!C15 -> 163785.6 | C14: =(1+$B$7)^2 -> 1.3924 | D14: =B14/C14 -> 117628.27 | E14: =E13+D14 -> -706948
A15: Año 3 | B15: ='Pro-Forma'!D15 -> 410081.66 | C15: =(1+$B$7)^3 -> 1.643032 | D15: =B15/C15 -> 249588.36 | E15: =E14+D15 -> -457359.64
A16: Año 4 | B16: ='Pro-Forma'!E15 -> 768475.21 | C16: =(1+$B$7)^4 -> 1.9387778 | D16: =B16/C16 -> 396370.97 | E16: =E15+D16 -> -60988.677
A17: Año 5 | B17: ='Pro-Forma'!F15 -> 1267819.9 | C17: =(1+$B$7)^5 -> 2.2877578 | D17: =B17/C17 -> 554175.74 | E17: =E16+D17 -> 493187.06
A19: VPN (Valor Presente Neto) | B19: =SUM(D12:D18) -> 493187.06 | E19: Suma de todos los VP
A20: TIR (Tasa Interna de Retorno) | B20: =IRR(B12:B17) -> 0.32580209 | E20: Tasa que hace VPN = 0
A22: REGLA DE DECISIÓN
A23: VPN > 0? | B23: =IF(B19>0,"SÍ ✓","NO ✗") -> SÍ ✓
A24: TIR > TMAR? | B24: =IF(B20>B7,"SÍ ✓","NO ✗") -> SÍ ✓
A25: DECISIÓN | B25: =IF(AND(B19>0,B20>B7),"INVERTIR","NO INVERTIR") -> INVERTIR
A28: ANÁLISIS DE SENSIBILIDAD — VPN vs Tasa de Descuento
A29: Tasa de descuento | B29: VPN | E29: Interpretación
A30: 0.05 | B30: =NPV(A30,B13:B17)+B12 -> 1306970.2 | E30: =IF(B30>0,"Aceptar","Rechazar") -> Aceptar
A31: 0.1 | B31: =NPV(A31,B13:B17)+B12 -> 932828.44 | E31: =IF(B31>0,"Aceptar","Rechazar") -> Aceptar
A32: 0.15 | B32: =NPV(A32,B13:B17)+B12 -> 639276.48 | E32: =IF(B32>0,"Aceptar","Rechazar") -> Aceptar
A33: 0.18 | B33: =NPV(A33,B13:B17)+B12 -> 493187.06 | E33: =IF(B33>0,"Aceptar","Rechazar") -> Aceptar
A34: 0.2 | B34: =NPV(A34,B13:B17)+B12 -> 406163.68 | E34: =IF(B34>0,"Aceptar","Rechazar") -> Aceptar
A35: 0.25 | B35: =NPV(A35,B13:B17)+B12 -> 218991.25 | E35: =IF(B35>0,"Aceptar","Rechazar") -> Aceptar
A36: 0.3 | B36: =NPV(A36,B13:B17)+B12 -> 67172.045 | E36: =IF(B36>0,"Aceptar","Rechazar") -> Aceptar
